Modules/Azure.py
Modules/Cloud.py
Modules/GCP.py
Modules/__init__.py
stoneclivmcreator-0.1.data/scripts/stone_cli.py
stoneclivmcreator-0.1.dist-info/METADATA
stoneclivmcreator-0.1.dist-info/WHEEL
stoneclivmcreator-0.1.dist-info/top_level.txt
stoneclivmcreator-0.1.dist-info/RECORD
